ansys/test/package/__init__.py
ansys_test_package-0.1.dev0.dist-info/LICENSE
ansys_test_package-0.1.dev0.dist-info/WHEEL
ansys_test_package-0.1.dev0.dist-info/METADATA
ansys_test_package-0.1.dev0.dist-info/RECORD
